docparser/__init__.py
docparser/doc_parser_factory.py
docparser/config/__init__.py
docparser/config/config_manager.py
docparser/config/excel/__init__.py
docparser/config/excel/action_config.py
docparser/config/excel/block_config.py
docparser/config/excel/custom_fields.py
docparser/config/excel/enums.py
docparser/config/excel/excel2_document_config.py
docparser/config/excel/excel_document_config.py
docparser/config/excel/kv_rule_config.py
docparser/config/excel/rect_config.py
docparser/config/excel/rule_config.py
docparser/config/excel/table_behavior_config.py
docparser/config/excel/table_block_config.py
docparser/config/excel/table_rule_config.py
docparser/config/excel/text_block_config.py
docparser/config/html/__init__.py
docparser/config/html/html_document_config.py
docparser/config/html/html_document_item_config.py
docparser/config/html/html_document_table_item_config.py
docparser/config/html/html_document_text_item_config.py
docparser/core/__init__.py
docparser/core/action_data_parser.py
docparser/core/behavior_base.py
docparser/core/behavior_data_parser.py
docparser/core/data_parser_base.py
docparser/core/document_parser_base.py
docparser/core/easy_cache.py
docparser/core/kv_data_parser.py
docparser/core/rect.py
docparser/core/table_data_parser.py
docparser/core/table_virtual_block.py
docparser/core/text_virtual_block.py
docparser/core/tools.py
docparser/core/utils.py
docparser/core/virtual_block.py
docparser/core/virtual_block_builder.py
docparser/extends/__init__.py
docparser/extends/cma_an_table_virtual_block.py
docparser/implements/__init__.py
docparser/implements/default_text_virtual_block.py
docparser/implements/excel2_document_parser.py
docparser/implements/excel_document_parser.py
docparser/implements/html_document_parser.py
docparser/implements/mixed_table_virtual_block.py
docparser/implements/standard_table_virtual_block.py
docparser/implements/text_document_parser.py
docparser/plugins/__init__.py
docparser/plugins/address_repair_behavior.py
CoDocParser-0.2.49.dist-info/LICENSE.txt
CoDocParser-0.2.49.dist-info/METADATA
CoDocParser-0.2.49.dist-info/WHEEL
CoDocParser-0.2.49.dist-info/top_level.txt
CoDocParser-0.2.49.dist-info/RECORD
