Metadata-Version: 2.1
Name: CoDocParser
Version: 0.2.49
Summary: 文档解析器
Home-page: https://www.cityocean.com
Author: CityOcean
Author-email: it@cityocean.com
License: GPL
Keywords: document,parser
Platform: UNKNOWN
Classifier: Intended Audience :: Developers
Classifier: License :: OSI Approved :: BSD License
Classifier: Programming Language :: Python
Classifier: Programming Language :: Python :: 3.8
Classifier: Programming Language :: Python :: 3.9
Classifier: Operating System :: OS Independent
Classifier: Topic :: Software Development :: Libraries :: Python Modules
Requires-Python: >=2.7, !=3.0.*, !=3.1.*, !=3.2.*, !=3.3.*, !=3.4.*, !=3.5.*
License-File: LICENSE.txt
Requires-Dist: pdfminer
Requires-Dist: marshmallow
Requires-Dist: lxml
Requires-Dist: pandas
Requires-Dist: numpy
Requires-Dist: parse
Requires-Dist: chardet
Provides-Extra: build
Requires-Dist: wheel ; extra == 'build'
Requires-Dist: twine ; extra == 'build'
